{
  "id": 7776564904017,
  "title": "Women's Silver Rainbow Gem Ring – Elegant Statement Jewelry",
  "body_html": "<p>\n <span style=\"color: inherit;\">Add a splash of color to your style with this stunning silver ring, featuring vibrant rainbow gemstones. Designed in a modern European style, it’s the perfect accessory to elevate both casual and formal looks.</span>\n</p>\n<p>✅ Eye-catching rainbow gem design </p>\n<p>✅ High-quality silver construction </p>\n<p>✅ Elegant and versatile for all occasions </p>\n<p>✅ Available in sizes 6–11 for the perfect fit</p>\n<p></p>\n<p>\n <br>\n</p>\n<p>\n <br>\n</p>",
  "vendor": "3",
  "product_type": "0",
  "created_at": "2025-05-01T13:21:49+03:00",
  "handle": "womens-silver-rainbow-gem-ring-elegant-statement-jewelry",
  "updated_at": "2025-07-07T00:41:31+03:00",
  "published_at": "2025-05-01T13:21:57+03:00",
  "template_suffix": null,
  "published_scope": "global",
  "tags": "",
  "status": "active",
  "admin_graphql_api_id": "gid://shopify/Product/7776564904017",
  "variants": [
    {
      "product_id": 7776564904017,
      "id": 42406684295249,
      "title": "Color / 10 number",
      "price": "14.00",
      "position": 1,
      "inventory_policy": "deny",
      "compare_at_price": null,
      "option1": "Color",
      "option2": "10 number",
      "option3": null,
      "created_at": "2025-05-01T13:21:54+03:00",
      "updated_at": "2025-05-05T00:17:45+03:00",
      "taxable": false,
      "barcode": null,
      "fulfillment_service": "manual",
      "grams": 3,
      "inventory_management": "shopify",
      "requires_shipping": true,
      "sku": "CJZBGJBS00050-Color-10 number",
      "weight": 3.0,
      "weight_unit": "g",
      "inventory_item_id": 44491269210193,
      "inventory_quantity": 10200,
      "old_inventory_quantity": 10200,
      "admin_graphql_api_id": "gid://shopify/ProductVariant/42406684295249",
      "image_id": 35646579015761
    },
    {
      "product_id": 7776564904017,
      "id": 42406684328017,
      "title": "Color / 11 number",
      "price": "14.00",
      "position": 2,
      "inventory_policy": "deny",
      "compare_at_price": null,
      "option1": "Color",
      "option2": "11 number",
      "option3": null,
      "created_at": "2025-05-01T13:21:54+03:00",
      "updated_at": "2025-05-05T00:17:45+03:00",
      "taxable": false,
      "barcode": null,
      "fulfillment_service": "manual",
      "grams": 4,
      "inventory_management": "shopify",
      "requires_shipping": true,
      "sku": "CJZBGJBS00050-Color-11 number",
      "weight": 4.0,
      "weight_unit": "g",
      "inventory_item_id": 44491269242961,
      "inventory_quantity": 11070,
      "old_inventory_quantity": 11070,
      "admin_graphql_api_id": "gid://shopify/ProductVariant/42406684328017",
      "image_id": 35646579015761
    },
    {
      "product_id": 7776564904017,
      "id": 42406684360785,
      "title": "Color / 6 number",
      "price": "14.00",
      "position": 3,
      "inventory_policy": "deny",
      "compare_at_price": null,
      "option1": "Color",
      "option2": "6 number",
      "option3": null,
      "created_at": "2025-05-01T13:21:54+03:00",
      "updated_at": "2025-05-05T00:17:45+03:00",
      "taxable": false,
      "barcode": null,
      "fulfillment_service": "manual",
      "grams": 3,
      "inventory_management": "shopify",
      "requires_shipping": true,
      "sku": "CJZBGJBS00050-Color-6 number",
      "weight": 3.0,
      "weight_unit": "g",
      "inventory_item_id": 44491269275729,
      "inventory_quantity": 13412,
      "old_inventory_quantity": 13412,
      "admin_graphql_api_id": "gid://shopify/ProductVariant/42406684360785",
      "image_id": 35646579015761
    },
    {
      "product_id": 7776564904017,
      "id": 42406684393553,
      "title": "Color / 7 number",
      "price": "14.00",
      "position": 4,
      "inventory_policy": "deny",
      "compare_at_price": null,
      "option1": "Color",
      "option2": "7 number",
      "option3": null,
      "created_at": "2025-05-01T13:21:54+03:00",
      "updated_at": "2025-05-05T00:17:45+03:00",
      "taxable": false,
      "barcode": null,
      "fulfillment_service": "manual",
      "grams": 3,
      "inventory_management": "shopify",
      "requires_shipping": true,
      "sku": "CJZBGJBS00050-Color-7 number",
      "weight": 3.0,
      "weight_unit": "g",
      "inventory_item_id": 44491269308497,
      "inventory_quantity": 13513,
      "old_inventory_quantity": 13513,
      "admin_graphql_api_id": "gid://shopify/ProductVariant/42406684393553",
      "image_id": 35646579015761
    },
    {
      "product_id": 7776564904017,
      "id": 42406684426321,
      "title": "Color / 8 number",
      "price": "14.00",
      "position": 5,
      "inventory_policy": "deny",
      "compare_at_price": null,
      "option1": "Color",
      "option2": "8 number",
      "option3": null,
      "created_at": "2025-05-01T13:21:54+03:00",
      "updated_at": "2025-05-05T00:17:45+03:00",
      "taxable": false,
      "barcode": null,
      "fulfillment_service": "manual",
      "grams": 3,
      "inventory_management": "shopify",
      "requires_shipping": true,
      "sku": "CJZBGJBS00050-Color-8 number",
      "weight": 3.0,
      "weight_unit": "g",
      "inventory_item_id": 44491269341265,
      "inventory_quantity": 14635,
      "old_inventory_quantity": 14635,
      "admin_graphql_api_id": "gid://shopify/ProductVariant/42406684426321",
      "image_id": 35646579015761
    },
    {
      "product_id": 7776564904017,
      "id": 42406684459089,
      "title": "Color / 9 number",
      "price": "14.00",
      "position": 6,
      "inventory_policy": "deny",
      "compare_at_price": null,
      "option1": "Color",
      "option2": "9 number",
      "option3": null,
      "created_at": "2025-05-01T13:21:54+03:00",
      "updated_at": "2025-05-05T00:17:45+03:00",
      "taxable": false,
      "barcode": null,
      "fulfillment_service": "manual",
      "grams": 3,
      "inventory_management": "shopify",
      "requires_shipping": true,
      "sku": "CJZBGJBS00050-Color-9 number",
      "weight": 3.0,
      "weight_unit": "g",
      "inventory_item_id": 44491269374033,
      "inventory_quantity": 12928,
      "old_inventory_quantity": 12928,
      "admin_graphql_api_id": "gid://shopify/ProductVariant/42406684459089",
      "image_id": 35646579015761
    }
  ],
  "options": [
    {
      "product_id": 7776564904017,
      "id": 9893816402001,
      "name": "Color",
      "position": 1,
      "values": [
        "Color"
      ]
    },
    {
      "product_id": 7776564904017,
      "id": 9893816434769,
      "name": "Size",
      "position": 2,
      "values": [
        "10 number",
        "11 number",
        "6 number",
        "7 number",
        "8 number",
        "9 number"
      ]
    }
  ],
  "images": [
    {
      "id": 35646578622545,
      "alt": null,
      "position": 1,
      "product_id": 7776564904017,
      "created_at": "2025-05-01T13:21:50+03:00",
      "updated_at": "2025-05-01T13:21:52+03:00",
      "admin_graphql_api_id": "gid://shopify/ProductImage/35646578622545",
      "width": 797,
      "height": 797,
      "src": "https://cdn.shopify.com/s/files/1/0665/9014/6641/files/4255234988_149182637_fad260cd-3d26-40fe-a001-a7233ff75402.jpg?v=1746094912",
      "variant_ids": []
    },
    {
      "id": 35646578851921,
      "alt": null,
      "position": 2,
      "product_id": 7776564904017,
      "created_at": "2025-05-01T13:21:53+03:00",
      "updated_at": "2025-05-01T13:21:54+03:00",
      "admin_graphql_api_id": "gid://shopify/ProductImage/35646578851921",
      "width": 797,
      "height": 797,
      "src": "https://cdn.shopify.com/s/files/1/0665/9014/6641/files/4258041096_149182637_717abe50-7e21-4703-af20-c5098bf8b79c.jpg?v=1746094914",
      "variant_ids": []
    },
    {
      "id": 35646578950225,
      "alt": null,
      "position": 3,
      "product_id": 7776564904017,
      "created_at": "2025-05-01T13:21:54+03:00",
      "updated_at": "2025-05-01T13:21:56+03:00",
      "admin_graphql_api_id": "gid://shopify/ProductImage/35646578950225",
      "width": 797,
      "height": 797,
      "src": "https://cdn.shopify.com/s/files/1/0665/9014/6641/files/4255249759_149182637_2e01f18b-d91e-4f6d-ad89-dd856e03ec06.jpg?v=1746094916",
      "variant_ids": []
    },
    {
      "id": 35646579015761,
      "alt": null,
      "position": 4,
      "product_id": 7776564904017,
      "created_at": "2025-05-01T13:21:55+03:00",
      "updated_at": "2025-05-01T13:21:56+03:00",
      "admin_graphql_api_id": "gid://shopify/ProductImage/35646579015761",
      "width": 797,
      "height": 797,
      "src": "https://cdn.shopify.com/s/files/1/0665/9014/6641/files/4255234988_149182637_c2987ea9-31ae-411d-888d-3e5e0be571ec.jpg?v=1746094916",
      "variant_ids": [
        42406684295249,
        42406684328017,
        42406684360785,
        42406684393553,
        42406684426321,
        42406684459089
      ]
    }
  ],
  "image": {
    "id": 35646578622545,
    "alt": null,
    "position": 1,
    "product_id": 7776564904017,
    "created_at": "2025-05-01T13:21:50+03:00",
    "updated_at": "2025-05-01T13:21:52+03:00",
    "admin_graphql_api_id": "gid://shopify/ProductImage/35646578622545",
    "width": 797,
    "height": 797,
    "src": "https://cdn.shopify.com/s/files/1/0665/9014/6641/files/4255234988_149182637_fad260cd-3d26-40fe-a001-a7233ff75402.jpg?v=1746094912",
    "variant_ids": []
  }
}